rsilk/__init__.py
rsilk/_silk.cpython-39-darwin.so
rsilk/_silk.pyi
rsilk/utils.py
rsilk-0.1.4.dist-info/LICENSE
rsilk-0.1.4.dist-info/METADATA
rsilk-0.1.4.dist-info/WHEEL
rsilk-0.1.4.dist-info/top_level.txt
rsilk-0.1.4.dist-info/RECORD
