Metadata-Version: 2.1
Name: rsilk
Version: 0.1.4
Summary: silk encoding and decoding for python
Home-page: https://github.com/synodriver/rsilk
Author: synodriver
Author-email: diguohuangjiajinweijun@gmail.com
License: MIT
Keywords: silk,pcm,audio
Platform: UNKNOWN
Classifier: Development Status :: 5 - Production/Stable
Classifier: Operating System :: OS Independent
Classifier: License :: OSI Approved :: MIT License
Classifier: Topic :: Multimedia :: Sound/Audio
Classifier: Programming Language :: Rust
Classifier: Programming Language :: Python
Classifier: Programming Language :: Python :: 3.7
Classifier: Programming Language :: Python :: 3.8
Classifier: Programming Language :: Python :: 3.9
Classifier: Programming Language :: Python :: 3.10
Classifier: Programming Language :: Python :: Implementation :: CPython
Requires-Python: >=3.6
License-File: LICENSE
